urlstd/__init__.py
urlstd/data/uri-schemes-1.csv.gz
urlstd/error.py
urlstd/parse.py
urlstd-2023.7.26.1.dist-info/LICENSE
urlstd-2023.7.26.1.dist-info/METADATA
urlstd-2023.7.26.1.dist-info/WHEEL
urlstd-2023.7.26.1.dist-info/RECORD
