Metadata-Version: 2.1
Name: urlstd
Version: 2023.7.26.1
Summary: Python implementation of the WHATWG URL Standard
Home-page: https://github.com/miute/urlstd
License: MIT
Keywords: url,whatwg-url,url-standard,url-parser,url-parsing
Author: Tetsuya Miura
Author-email: miute.dev@gmail.com
Requires-Python: >=3.8,<4.0
Classifier: Development Status :: 5 - Production/Stable
Classifier: Intended Audience :: Developers
Classifier: License :: OSI Approved :: MIT License
Classifier: Operating System :: Microsoft :: Windows
Classifier: Operating System :: POSIX
Classifier: Programming Language :: Python :: 3
Classifier: Programming Language :: Python :: 3.8
Classifier: Programming Language :: Python :: 3.9
Classifier: Programming Language :: Python :: 3.10
Classifier: Programming Language :: Python :: 3.11
Classifier: Programming Language :: Python :: 3 :: Only
Classifier: Topic :: Internet
Classifier: Topic :: Software Development :: Libraries
Requires-Dist: icupy (>=0.11.0)
Project-URL: Documentation, https://miute.github.io/urlstd/
